{
  "$schema_version": "0.1.0",
  "import_version": {
    "build": "GRCh37",
    "table_group": "clinvar",
    "version": "20210728"
  },
  "by_chrom": {
    "chr1": 87380,
    "chr10": 40531,
    "chr11": 64585,
    "chr12": 47959,
    "chr13": 29072,
    "chr14": 33254,
    "chr15": 37637,
    "chr16": 58862,
    "chr17": 75205,
    "chr18": 18304,
    "chr19": 50604,
    "chr2": 110437,
    "chr20": 19767,
    "chr21": 12313,
    "chr22": 21019,
    "chr3": 55079,
    "chr4": 33663,
    "chr5": 57454,
    "chr6": 47114,
    "chr7": 50101,
    "chr8": 36341,
    "chr9": 49046,
    "chrM": 2834,
    "chrX": 44708,
    "chrY": 46,
    ".": 1083315
  },
  "by_col": {
    "release": {
      "type": "ENUM",
      "values": [
        "GRCh37"
      ]
    },
    "chromosome": {
      "type": "ENUM",
      "values": [
        "chr1",
        "chr10",
        "chr11",
        "chr12",
        "chr13",
        "chr14",
        "chr15",
        "chr16",
        "chr17",
        "chr18",
        "chr19",
        "chr2",
        "chr20",
        "chr21",
        "chr22",
        "chr3",
        "chr4",
        "chr5",
        "chr6",
        "chr7",
        "chr8",
        "chr9",
        "chrM",
        "chrX",
        "chrY"
      ]
    },
    "start": {
      "type": "INT"
    },
    "end": {
      "type": "INT"
    },
    "bin": {
      "type": "INT"
    },
    "reference": {
      "type": "DNA"
    },
    "alternative": {
      "type": "DNA"
    },
    "variation_type": {
      "type": "ENUM",
      "values": [
        "indel",
        "mnv",
        "snv"
      ]
    },
    "symbols": {
      "type": "STRING"
    },
    "hgnc_ids": {
      "type": "STRING"
    },
    "vcv": {
      "type": "STRING"
    },
    "point_rating": {
      "type": "INT"
    },
    "pathogenicity": {
      "type": "ENUM",
      "values": [
        "benign",
        "likely benign",
        "likely pathogenic",
        "pathogenic",
        "uncertain significance"
      ]
    },
    "review_status": {
      "type": "ENUM",
      "values": [
        "criteria provided, conflicting interpretations",
        "criteria provided, single submitter",
        "multiple submitters, no conflicts",
        "no assertion criteria provided",
        "no assertion provided",
        "practice guideline",
        "reviewed by expert panel"
      ]
    },
    "pathogenicity_summary": {
      "type": "ENUM",
      "values": [
        "benign",
        "likely benign",
        "likely benign(1); benign(1)",
        "likely pathogenic",
        "likely pathogenic(1); benign(1)",
        "likely pathogenic(1); likely benign(1)",
        "likely pathogenic(1); likely benign(1); benign(1)",
        "likely pathogenic(1); uncertain significance(1)",
        "likely pathogenic(1); uncertain significance(1); benign(1)",
        "likely pathogenic(1); uncertain significance(1); likely benign(1)",
        "likely pathogenic(1); uncertain significance(1); likely benign(1); benign(1)",
        "pathogenic",
        "pathogenic(1); benign(1)",
        "pathogenic(1); likely benign(1)",
        "pathogenic(1); likely benign(1); benign(1)",
        "pathogenic(1); likely pathogenic(1)",
        "pathogenic(1); likely pathogenic(1); benign(1)",
        "pathogenic(1); likely pathogenic(1); likely benign(1)",
        "pathogenic(1); likely pathogenic(1); likely benign(1); benign(1)",
        "pathogenic(1); likely pathogenic(1); uncertain significance(1)",
        "pathogenic(1); likely pathogenic(1); uncertain significance(1); benign(1)",
        "pathogenic(1); likely pathogenic(1); uncertain significance(1); likely benign(1)",
        "pathogenic(1); likely pathogenic(1); uncertain significance(1); likely benign(1); benign(1)",
        "pathogenic(1); uncertain significance(1)",
        "pathogenic(1); uncertain significance(1); benign(1)",
        "pathogenic(1); uncertain significance(1); likely benign(1)",
        "pathogenic(1); uncertain significance(1); likely benign(1); benign(1)",
        "uncertain significance",
        "uncertain significance(1); benign(1)",
        "uncertain significance(1); likely benign(1)",
        "uncertain significance(1); likely benign(1); benign(1)"
      ]
    },
    "details": {
      "type": "STRING"
    }
  }
}
