{
  "$schema_version": "0.1.0",
  "import_version": {
    "build": "noref",
    "table_group": "hpo",
    "version": "20210728"
  },
  "by_chrom": {
    ".": 230758
  },
  "by_col": {
    "database_id": {
      "type": "STRING"
    },
    "name": {
      "type": "STRING"
    },
    "qualifier": {
      "type": "ENUM",
      "values": [
        "",
        "NOT"
      ]
    },
    "hpo_id": {
      "type": "STRING"
    },
    "reference": {
      "type": "STRING"
    },
    "evidence": {
      "type": "ENUM",
      "values": [
        "IEA",
        "PCS",
        "TAS"
      ]
    },
    "onset": {
      "type": "ENUM",
      "values": [
        "",
        "HP:0003577",
        "HP:0003581",
        "HP:0003584",
        "HP:0003593",
        "HP:0003596",
        "HP:0003621",
        "HP:0003623",
        "HP:0003674",
        "HP:0011461",
        "HP:0011462",
        "HP:0011463",
        "HP:0030674"
      ]
    },
    "frequency": {
      "type": "STRING"
    },
    "sex": {
      "type": "ENUM",
      "values": [
        "",
        "FEMALE",
        "MALE",
        "female",
        "male"
      ]
    },
    "modifier": {
      "type": "ENUM",
      "values": [
        "",
        "HP:0003676",
        "HP:0003680",
        "HP:0003831",
        "HP:0011010",
        "HP:0012825",
        "HP:0012826",
        "HP:0012827",
        "HP:0012828",
        "HP:0012828;HP:0012828",
        "HP:0012829",
        "HP:0012832",
        "HP:0012833",
        "HP:0012833;HP:0012833",
        "HP:0012834",
        "HP:0012837",
        "HP:0012839",
        "HP:0012840",
        "HP:0025206",
        "HP:0025206;HP:0025206",
        "HP:0025206;HP:0025206;HP:0025206",
        "HP:0025206;HP:0025303",
        "HP:0025215",
        "HP:0025221",
        "HP:0025292",
        "HP:0025301",
        "HP:0025303",
        "HP:0025334",
        "HP:0025377",
        "HP:0025377;HP:0025377",
        "HP:0030650",
        "HP:0030651",
        "HP:0031375",
        "HP:0031796",
        "HP:0031796;HP:0031796",
        "HP:0032365",
        "HP:0033184",
        "HP:0033185",
        "HP:0033185;HP:0033185",
        "HP:0033198",
        "HP:0500261"
      ]
    },
    "aspect": {
      "type": "ENUM",
      "values": [
        "C",
        "I",
        "M",
        "P"
      ]
    },
    "biocuration": {
      "type": "STRING"
    },
    "omim_id": {
      "type": "STRING"
    },
    "decipher_id": {
      "type": "ENUM",
      "values": [
        "",
        "1",
        "14",
        "15",
        "16",
        "17",
        "18",
        "19",
        "2",
        "20",
        "21",
        "29",
        "3",
        "31",
        "32",
        "34",
        "35",
        "37",
        "38",
        "39",
        "4",
        "42",
        "43",
        "44",
        "45",
        "46",
        "47",
        "48",
        "51",
        "52",
        "53",
        "54",
        "57",
        "58",
        "59",
        "62",
        "65",
        "66",
        "67",
        "68",
        "70",
        "72",
        "74",
        "76",
        "8",
        "81",
        "85",
        "92"
      ]
    },
    "orpha_id": {
      "type": "ENUM",
      "values": [
        "",
        "10",
        "100",
        "1000",
        "100006",
        "100008",
        "100024",
        "100025",
        "100026",
        "100050",
        "100069",
        "100070",
        "100073",
        "100075",
        "100076",
        "100077",
        "100078",
        "100079",
        "100080",
        "100081",
        "100082",
        "100083",
        "100084",
        "100085",
        "100086",
        "100093",
        "1001",
        "100100",
        "1003",
        "1005",
        "1006",
        "1008",
        "100924",
        "100973",
        "100976",
        "100984",
        "100985",
        "100986",
        "100988",
        "100989",
        "100991",
        "100993",
        "100994",
        "100995",
        "100996",
        "100997",
        "100998",
        "100999",
        "101",
        "1010",
        "101000",
        "101001",
        "101003",
        "101004",
        "101005",
        "101006",
        "101007",
        "101008",
        "101009",
        "101010",
        "101011",
        "101016",
        "101028",
        "101029",
        "101030",
        "101039",
        "101041",
        "101046",
        "101070",
        "101071",
        "101075",
        "101076",
        "101077",
        "101078",
        "101081",
        "101082",
        "101085",
        "101096",
        "101108",
        "101109",
        "101110",
        "101111",
        "101112",
        "101150",
        "101330",
        "1014",
        "101685",
        "1018",
        "102",
        "1020",
        "1021",
        "1027",
        "1028",
        "1031",
        "1035",
        "103910",
        "104",
        "1040",
        "1041",
        "1046",
        "1048",
        "105",
        "1051",
        "1052",
        "1053",
        "1054",
        "1055",
        "1059",
        "1062",
        "1063",
        "1064",
        "1065",
        "1067",
        "1068",
        "1069",
        "107",
        "1071",
        "1072",
        "1074",
        "1077",
        "1078",
        "108",
        "1083",
        "1084",
        "109",
        "1094",
        "11",
        "110",
        "1101",
        "1104",
        "1106",
        "111",
        "1110",
        "1112",
        "1113",
        "1114",
        "1116",
        "1117",
        "1118",
        "112",
        "1120",
        "1122",
        "1123",
        "1129",
        "113",
        "1131",
        "1133",
        "1134",
        "1135",
        "1136",
        "114",
        "1143",
        "1144",
        "1145",
        "1146",
        "1147",
        "1149",
        "115",
        "1150",
        "1154",
        "1159",
        "116",
        "1160",
        "1163",
        "1164",
        "1166",
        "1168",
        "117",
        "1170",
        "1171",
        "1173",
        "1174",
        "1175",
        "1177",
        "1178",
        "1179",
        "118",
        "1180",
        "1182",
        "1183",
        "1184",
        "1185",
        "1186",
        "1187",
        "1188",
        "119",
        "1190",
        "1192",
        "1193",
        "1194",
        "1195",
        "1198",
        "1199",
        "1200",
        "1201",
        "1202",
        "1203",
        "1208",
        "1209",
        "1214",
        "1215",
        "1216",
        "122",
        "1221",
        "1225",
        "1226",
        "1227",
        "1228",
        "1229",
        "123",
        "1231",
        "1234",
        "1236",
        "1237",
        "124",
        "1240",
        "1241",
        "1243",
        "1248",
        "125",
        "1252",
        "1253",
        "1259",
        "126",
        "1261",
        "1262",
        "1263",
        "1264",
        "1267",
        "127",
        "1270",
        "1272",
        "1275",
        "1276",
        "1277",
        "1278",
        "129",
        "1292",
        "1295",
        "1296",
        "1297",
        "1299",
        "13",
        "130",
        "1300",
        "1302",
        "1303",
        "1304",
        "1305",
        "1306",
        "1307",
        "1308",
        "1309",
        "131",
        "1310",
        "1313",
        "1314",
        "1318",
        "1319",
        "132",
        "1320",
        "1321",
        "1323",
        "1325",
        "1326",
        "1327",
        "1328",
        "1329",
        "133",
        "1330",
        "1332",
        "1333",
        "1334",
        "1335",
        "1336",
        "1338",
        "134",
        "1340",
        "1342",
        "1344",
        "1345",
        "1349",
        "135",
        "1350",
        "1352",
        "1354",
        "1355",
        "1358",
        "1359",
        "136",
        "1361",
        "1366",
        "1368",
        "1369",
        "1373",
        "1375",
        "137596",
        "137599",
        "137608",
        "137634",
        "137667",
        "137675",
        "137686",
        "1377",
        "137754",
        "137817",
        "137831",
        "137834",
        "137867",
        "137888",
        "137898",
        "137902",
        "137914",
        "137935",
        "138",
        "1380",
        "1381",
        "1383",
        "1387",
        "1388",
        "1389",
        "1390",
        "1393",
        "139396",
        "139399",
        "1394",
        "139402",
        "139406",
        "139411",
        "139414",
        "139426",
        "139436",
        "139444",
        "139450",
        "139466",
        "139471",
        "139474",
        "139480",
        "139485",
        "139491",
        "139507",
        "139536",
        "139578",
        "1397",
        "1398",
        "1399",
        "14",
        "140",
        "1401",
        "140286",
        "1406",
        "140896",
        "140905",
        "140908",
        "140933",
        "140936",
        "140941",
        "140952",
        "140966",
        "140976",
        "140989",
        "141",
        "1410",
        "141091",
        "141096",
        "141127",
        "141179",
        "141184",
        "1412",
        "141291",
        "141333",
        "1414",
        "1416",
        "142",
        "1422",
        "1423",
        "1425",
        "1426",
        "1427",
        "1429",
        "143",
        "1433",
        "1435",
        "1436",
        "1437",
        "1438",
        "1439",
        "144",
        "1445",
        "1446",
        "1447",
        "1448",
        "1449",
        "145",
        "1450",
        "1451",
        "1452",
        "1453",
        "1454",
        "1455",
        "1457",
        "1458",
        "1461",
        "1465",
        "1466",
        "1467",
        "147",
        "1471",
        "1473",
        "1475",
        "1479",
        "148",
        "1484",
        "1486",
        "1487",
        "1488",
        "1490",
        "1493",
        "1495",
        "1496",
        "1497",
        "15",
        "1501",
        "1505",
        "1506",
        "1507",
        "1508",
        "1509",
        "1512",
        "1513",
        "1514",
        "1515",
        "1516",
        "1517",
        "1519",
        "1520",
        "1521",
        "1522",
        "1525",
        "1527",
        "1528",
        "1529",
        "1532",
        "1533",
        "1538",
        "154",
        "1540",
        "1545",
        "1546",
        "1547",
        "1548",
        "1549",
        "1551",
        "1552",
        "1553",
        "1555",
        "1556",
        "156",
        "1560",
        "1562",
        "1563",
        "1566",
        "156728",
        "1568",
        "157",
        "1570",
        "1571",
        "1572",
        "157215",
        "1573",
        "1574",
        "157794",
        "157798",
        "1578",
        "157801",
        "157835",
        "157846",
        "157850",
        "157941",
        "157946",
        "157954",
        "157965",
        "157973",
        "157991",
        "157997",
        "158",
        "1580",
        "158000",
        "158003",
        "158008",
        "158014",
        "158022",
        "158025",
        "158029",
        "1581",
        "158668",
        "158673",
        "158676",
        "158681",
        "158684",
        "158687",
        "1587",
        "159",
        "1590",
        "1596",
        "1597",
        "1598",
        "16",
        "160",
        "1600",
        "160148",
        "1606",
        "1617",
        "1620",
        "1621",
        "163",
        "163596",
        "1636",
        "163634",
        "163649",
        "163654",
        "163665",
        "163690",
        "163693",
        "163703",
        "163721",
        "163727",
        "163746",
        "163934",
        "163937",
        "163956",
        "163961",
        "163966",
        "163971",
        "163976",
        "163979",
        "163985",
        "1642",
        "1643",
        "1646",
        "1647",
        "1652",
        "1653",
        "1655",
        "1656",
        "1657",
        "1658",
        "1659",
        "1660",
        "166002",
        "166011",
        "166016",
        "166024",
        "166035",
        "166063",
        "1661",
        "166100",
        "166108",
        "166113",
        "166119",
        "1662",
        "166272",
        "166277",
        "1665",
        "1666",
        "1667",
        "167",
        "1671",
        "1672",
        "1675",
        "167635",
        "1677",
        "168",
        "1681",
        "1682",
        "168486",
        "168491",
        "168549",
        "168555",
        "168558",
        "168563",
        "168569",
        "168572",
        "168577",
        "168593",
        "1686",
        "168624",
        "168782",
        "168796",
        "168811",
        "168816",
        "168829",
        "168984",
        "169",
        "169079",
        "169090",
        "169095",
        "169105",
        "169154",
        "169160",
        "169186",
        "169189",
        "1692",
        "1695",
        "169802",
        "169805",
        "1699",
        "17",
        "170",
        "1702",
        "1703",
        "1705",
        "1706",
        "1707",
        "1708",
        "171",
        "1713",
        "171430",
        "171433",
        "171436",
        "171439",
        "171442",
        "1715",
        "1716",
        "171607",
        "171612",
        "171617",
        "171622",
        "171629",
        "171673",
        "171695",
        "171703",
        "171719",
        "171829",
        "171839",
        "171844",
        "171851",
        "171860",
        "171863",
        "171866",
        "171876",
        "171881",
        "171929",
        "172",
        "1724",
        "1727",
        "173",
        "1738",
        "174",
        "1742",
        "1745",
        "175",
        "1752",
        "1756",
        "1757",
        "1759",
        "1762",
        "1764",
        "1765",
        "1766",
        "177",
        "1770",
        "1772",
        "1775",
        "1777",
        "1778",
        "1779",
        "177901",
        "177904",
        "177907",
        "177910",
        "177926",
        "1780",
        "178029",
        "178145",
        "178148",
        "1782",
        "178303",
        "178320",
        "178333",
        "178377",
        "1784",
        "178400",
        "178464",
        "178469",
        "178475",
        "178478",
        "178481",
        "178487",
        "178509",
        "1786",
        "1787",
        "1788",
        "179",
        "1790",
        "1791",
        "1794",
        "179494",
        "1795",
        "1797",
        "1798",
        "1799",
        "18",
        "180",
        "1801",
        "1802",
        "180229",
        "1803",
        "1806",
        "1807",
        "1808",
        "1809",
        "181",
        "1810",
        "1811",
        "1812",
        "181393",
        "1816",
        "1818",
        "182",
        "182050",
        "1822",
        "1824",
        "1825",
        "1826",
        "1827",
        "183",
        "1830",
        "1832",
        "1834",
        "1836",
        "1837",
        "183707",
        "183713",
        "1839",
        "184",
        "1842",
        "1848",
        "185",
        "1852",
        "1855",
        "1856",
        "1858",
        "186",
        "1860",
        "1861",
        "1865",
        "1867",
        "1871",
        "1872",
        "1873",
        "1875",
        "1876",
        "1878",
        "1879",
        "188",
        "1880",
        "1882",
        "1883",
        "1885",
        "189",
        "1891",
        "1892",
        "189427",
        "189439",
        "1895",
        "1896",
        "1897",
        "1899",
        "190",
        "1900",
        "1901",
        "1906",
        "1908",
        "1909",
        "191",
        "1910",
        "1911",
        "1912",
        "1913",
        "1914",
        "1915",
        "1916",
        "1917",
        "1918",
        "1919",
        "192",
        "1920",
        "1923",
        "1926",
        "1927",
        "1928",
        "1929",
        "193",
        "1930",
        "1931",
        "1933",
        "1934",
        "1935",
        "1937",
        "1941",
        "1942",
        "1945",
        "1946",
        "1947",
        "1948",
        "1949",
        "195",
        "1951",
        "1952",
        "1954",
        "1955",
        "1959",
        "1962",
        "1964",
        "1968",
        "1969",
        "1970",
        "1972",
        "1973",
        "1974",
        "1979",
        "198",
        "1980",
        "1986",
        "1988",
        "199",
        "1991",
        "199241",
        "199244",
        "199251",
        "199267",
        "199276",
        "199296",
        "199299",
        "1993",
        "199302",
        "199306",
        "199310",
        "199318",
        "199343",
        "199351",
        "1995",
        "1997",
        "20",
        "2001",
        "2003",
        "2004",
        "2007",
        "2008",
        "201",
        "2010",
        "2013",
        "2015",
        "2016",
        "2017",
        "2019",
        "202",
        "2020",
        "2021",
        "2022",
        "2023",
        "2024",
        "2025",
        "2026",
        "2027",
        "2028",
        "2031",
        "2032",
        "2035",
        "2036",
        "2038",
        "204",
        "2040",
        "2041",
        "2044",
        "2045",
        "2047",
        "2048",
        "205",
        "2050",
        "2052",
        "2053",
        "2056",
        "2057",
        "2058",
        "2059",
        "2062",
        "2063",
        "2064",
        "206436",
        "206443",
        "206448",
        "206484",
        "2065",
        "206549",
        "206559",
        "206569",
        "206583",
        "2067",
        "2069",
        "207",
        "2070",
        "2072",
        "2073",
        "2074",
        "2075",
        "2077",
        "2078",
        "2083",
        "2084",
        "208441",
        "208444",
        "208447",
        "2085",
        "208513",
        "2086",
        "2088",
        "2089",
        "208981",
        "2090",
        "209004",
        "2091",
        "2092",
        "2095",
        "2097",
        "2098",
        "209902",
        "209905",
        "209908",
        "209943",
        "209951",
        "209956",
        "209967",
        "209970",
        "209981",
        "2101",
        "210110",
        "210122",
        "210128",
        "210136",
        "210272",
        "2104",
        "210571",
        "2107",
        "2108",
        "211",
        "2110",
        "211017",
        "211067",
        "2111",
        "2114",
        "2115",
        "2116",
        "2117",
        "2118",
        "2119",
        "212",
        "2123",
        "2126",
        "2128",
        "213",
        "2131",
        "2133",
        "2134",
        "2135",
        "2136",
        "2137",
        "2138",
        "2139",
        "214",
        "2140",
        "2141",
        "2143",
        "2145",
        "2148",
        "2149",
        "215",
        "2150",
        "2151",
        "2152",
        "2155",
        "2157",
        "2158",
        "2162",
        "2163",
        "2165",
        "2166",
        "216694",
        "2167",
        "216866",
        "216873",
        "2169",
        "217",
        "217012",
        "217017",
        "217085",
        "217093",
        "2172",
        "217260",
        "217266",
        "217335",
        "217340",
        "217346",
        "217377",
        "217385",
        "217390",
        "217563",
        "2176",
        "217607",
        "217622",
        "2177",
        "218",
        "2180",
        "2181",
        "2182",
        "2183",
        "2184",
        "2185",
        "2189",
        "219",
        "2196",
        "2197",
        "2198",
        "2199",
        "22",
        "220",
        "2200",
        "2201",
        "2202",
        "220295",
        "2203",
        "220386",
        "220393",
        "2204",
        "220402",
        "220460",
        "220493",
        "220497",
        "2206",
        "2209",
        "221",
        "221008",
        "221016",
        "221054",
        "221061",
        "221074",
        "221091",
        "221098",
        "2211",
        "221120",
        "221139",
        "2213",
        "2215",
        "2216",
        "2218",
        "222",
        "2220",
        "2221",
        "2222",
        "2228",
        "2229",
        "223",
        "2232",
        "2233",
        "2234",
        "2235",
        "2237",
        "2238",
        "2239",
        "2241",
        "2246",
        "2248",
        "2249",
        "225",
        "2250",
        "2251",
        "225147",
        "225154",
        "2252",
        "2253",
        "2255",
        "2256",
        "2257",
        "2258",
        "226",
        "2260",
        "2261",
        "226292",
        "226307",
        "226313",
        "226316",
        "2266",
        "2268",
        "2269",
        "227",
        "2271",
        "2273",
        "2274",
        "227510",
        "2278",
        "227982",
        "227990",
        "228116",
        "228119",
        "228123",
        "228169",
        "228190",
        "2282",
        "228240",
        "228277",
        "228302",
        "228305",
        "228308",
        "228312",
        "228360",
        "228371",
        "228384",
        "228390",
        "228396",
        "228399",
        "228402",
        "228410",
        "228415",
        "228426",
        "2285",
        "2287",
        "2289",
        "229",
        "2290",
        "2291",
        "2292",
        "2295",
        "2297",
        "229717",
        "2298",
        "2299",
        "23",
        "230",
        "2300",
        "2301",
        "2302",
        "2305",
        "2306",
        "2307",
        "2308",
        "230800",
        "230839",
        "230851",
        "2309",
        "231",
        "2310",
        "2311",
        "231111",
        "231137",
        "231140",
        "231144",
        "231147",
        "231154",
        "231160",
        "231169",
        "231178",
        "231183",
        "231214",
        "231222",
        "231226",
        "231237",
        "231242",
        "231249",
        "231393",
        "2314",
        "231401",
        "231445",
        "2315",
        "231568",
        "231580",
        "2316",
        "231625",
        "231632",
        "231720",
        "231736",
        "2318",
        "2319",
        "232",
        "2321",
        "2322",
        "2323",
        "2324",
        "2325",
        "2326",
        "2328",
        "233",
        "2330",
        "2331",
        "2332",
        "2334",
        "2337",
        "2339",
        "234",
        "2343",
        "2345",
        "2346",
        "2347",
        "2348",
        "2349",
        "235",
        "2356",
        "2357",
        "236",
        "2363",
        "2364",
        "2368",
        "2369",
        "237",
        "2370",
        "2373",
        "2374",
        "2375",
        "2377",
        "2378",
        "2379",
        "2380",
        "2382",
        "238329",
        "238446",
        "238455",
        "238459",
        "238468",
        "238578",
        "2386",
        "238606",
        "238624",
        "2387",
        "238722",
        "238750",
        "238769",
        "2388",
        "239",
        "2394",
        "2396",
        "2398",
        "2399",
        "240",
        "2400",
        "240071",
        "240085",
        "240094",
        "240103",
        "240112",
        "2406",
        "2408",
        "2409",
        "241",
        "2410",
        "2412",
        "2414",
        "242",
        "2429",
        "243",
        "2430",
        "2432",
        "243343",
        "2435",
        "2437",
        "2438",
        "244",
        "2440",
        "2442",
        "244242",
        "244310",
        "2444",
        "245",
        "2456",
        "2457",
        "246",
        "2461",
        "2462",
        "2463",
        "2466",
        "2470",
        "2471",
        "247234",
        "247245",
        "247257",
        "247262",
        "2473",
        "2475",
        "247525",
        "247585",
        "247598",
        "2476",
        "247604",
        "247691",
        "2477",
        "247768",
        "247798",
        "247806",
        "247815",
        "2479",
        "248",
        "2481",
        "248111",
        "2483",
        "2484",
        "2485",
        "2487",
        "2489",
        "249",
        "2491",
        "2492",
        "2494",
        "2495",
        "2496",
        "2497",
        "2499",
        "25",
        "2500",
        "2501",
        "2502",
        "2505",
        "2508",
        "250923",
        "250972",
        "250977",
        "250984",
        "250989",
        "250994",
        "250999",
        "2510",
        "251004",
        "251009",
        "251014",
        "251019",
        "251028",
        "251038",
        "251046",
        "251056",
        "251066",
        "251071",
        "251076",
        "2511",
        "2512",
        "251274",
        "251282",
        "2513",
        "251347",
        "251383",
        "251393",
        "2514",
        "2515",
        "251510",
        "2516",
        "251623",
        "251636",
        "251639",
        "251643",
        "2518",
        "2519",
        "251909",
        "251912",
        "251915",
        "251937",
        "251992",
        "252054",
        "2521",
        "252164",
        "252183",
        "2522",
        "2523",
        "2524",
        "2526",
        "2528",
        "2533",
        "2536",
        "2538",
        "254343",
        "254346",
        "254351",
        "254361",
        "254478",
        "254504",
        "254509",
        "254516",
        "254519",
        "254525",
        "254528",
        "254531",
        "254534",
        "2547",
        "254704",
        "254854",
        "254857",
        "254864",
        "254875",
        "254886",
        "254892",
        "2549",
        "254930",
        "255",
        "255138",
        "255182",
        "2552",
        "255210",
        "255241",
        "255249",
        "2554",
        "2556",
        "2557",
        "256",
        "2560",
        "2563",
        "2564",
        "257",
        "2570",
        "2571",
        "2572",
        "2573",
        "2574",
        "2575",
        "2576",
        "2578",
        "2579",
        "258",
        "2582",
        "2583",
        "2584",
        "2585",
        "2588",
        "2589",
        "2590",
        "2591",
        "2593",
        "2596",
        "25968",
        "2597",
        "2598",
        "26",
        "2604",
        "2608",
        "2609",
        "261",
        "2611",
        "261102",
        "261112",
        "261120",
        "261144",
        "261183",
        "261190",
        "261197",
        "2612",
        "261204",
        "261211",
        "261222",
        "261236",
        "261243",
        "261250",
        "261265",
        "261272",
        "261279",
        "261290",
        "261295",
        "2613",
        "261304",
        "261311",
        "261318",
        "261323",
        "261330",
        "261337",
        "261344",
        "261349",
        "26137",
        "2614",
        "261476",
        "261483",
        "261494",
        "261519",
        "261524",
        "261529",
        "261534",
        "261537",
        "261552",
        "261584",
        "2616",
        "261652",
        "2617",
        "2619",
        "261911",
        "262",
        "262767",
        "2631",
        "2632",
        "263297",
        "2633",
        "2634",
        "263410",
        "263455",
        "263458",
        "263463",
        "263487",
        "263494",
        "2635",
        "263501",
        "263508",
        "263516",
        "263534",
        "2636",
        "263665",
        "2637",
        "2639",
        "264200",
        "2643",
        "264450",
        "2645",
        "264580",
        "264675",
        "2655",
        "2658",
        "266",
        "2662",
        "2663",
        "2668",
        "2669",
        "267",
        "2671",
        "2672",
        "2673",
        "2678",
        "26790",
        "26791",
        "26792",
        "26793",
        "268",
        "2680",
        "268249",
        "268261",
        "2686",
        "2688",
        "268810",
        "268882",
        "268940",
        "268943",
        "268947",
        "269",
        "2690",
        "2695",
        "2698",
        "27",
        "270",
        "2701",
        "2703",
        "2704",
        "2707",
        "2710",
        "2712",
        "2714",
        "2715",
        "2717",
        "2719",
        "272",
        "2720",
        "2722",
        "2724",
        "2725",
        "2728",
        "2729",
        "273",
        "2730",
        "2732",
        "2736",
        "274",
        "2741",
        "2743",
        "2744",
        "2745",
        "2746",
        "275",
        "2750",
        "2751",
        "2752",
        "2753",
        "2754",
        "275543",
        "275555",
        "2756",
        "275761",
        "275766",
        "275864",
        "275872",
        "2759",
        "276",
        "2760",
        "276152",
        "276183",
        "276193",
        "276198",
        "2762",
        "276238",
        "276241",
        "276244",
        "276280",
        "276399",
        "2764",
        "276413",
        "276422",
        "276432",
        "276435",
        "276556",
        "276575",
        "276580",
        "276608",
        "276621",
        "276630",
        "2768",
        "2769",
        "277",
        "2770",
        "2771",
        "2772",
        "2773",
        "2774",
        "2776",
        "2777",
        "2779",
        "2780",
        "2785",
        "2786",
        "2787",
        "2788",
        "2789",
        "2790",
        "2791",
        "2792",
        "2793",
        "2795",
        "2796",
        "2798",
        "279882",
        "279914",
        "279947",
        "28",
        "280",
        "280062",
        "280071",
        "2801",
        "280195",
        "2802",
        "280200",
        "280210",
        "280219",
        "280224",
        "280229",
        "280234",
        "280333",
        "280356",
        "280365",
        "280384",
        "280397",
        "2804",
        "280633",
        "280651",
        "280679",
        "2807",
        "280763",
        "280779",
        "280785",
        "280794",
        "2808",
        "280914",
        "280921",
        "281",
        "281090",
        "281122",
        "281127",
        "2812",
        "281201",
        "2815",
        "2818",
        "2819",
        "2820",
        "2821",
        "282166",
        "2822",
        "2824",
        "2826",
        "2828",
        "2831",
        "2833",
        "2834",
        "2835",
        "2836",
        "28378",
        "2838",
        "2839",
        "284",
        "2840",
        "2841",
        "284160",
        "284169",
        "284180",
        "2842",
        "284227",
        "284271",
        "284282",
        "284289",
        "2843",
        "284324",
        "284332",
        "284339",
        "284388",
        "284400",
        "284417",
        "284426",
        "284454",
        "2847",
        "2849",
        "284979",
        "284984",
        "285",
        "2850",
        "2856",
        "286",
        "2863",
        "2865",
        "2866",
        "2867",
        "2868",
        "2869",
        "287",
        "2871",
        "2872",
        "2875",
        "2876",
        "2878",
        "2879",
        "288",
        "2884",
        "2885",
        "2886",
        "2889",
        "289",
        "2890",
        "2891",
        "289157",
        "289176",
        "289266",
        "289390",
        "289483",
        "289494",
        "289504",
        "289522",
        "289548",
        "289560",
        "289596",
        "2896",
        "289601",
        "2897",
        "2898",
        "289916",
        "29",
        "290",
        "2900",
        "2901",
        "2902",
        "2903",
        "2905",
        "2907",
        "29072",
        "29073",
        "2908",
        "2909",
        "291",
        "2911",
        "2912",
        "2916",
        "2917",
        "2919",
        "292",
        "2920",
        "29207",
        "2921",
        "2924",
        "2926",
        "2928",
        "2929",
        "293",
        "2930",
        "293168",
        "2932",
        "293381",
        "2935",
        "293603",
        "293621",
        "293707",
        "293725",
        "293807",
        "293812",
        "293843",
        "293939",
        "293948",
        "293964",
        "293967",
        "293978",
        "293987",
        "294",
        "2940",
        "294023",
        "2942",
        "294975",
        "295",
        "295036",
        "2953",
        "2956",
        "2958",
        "2959",
        "296",
        "2962",
        "2963",
        "2964",
        "2965",
        "2968",
        "2969",
        "297",
        "2970",
        "2971",
        "2972",
        "2973",
        "2975",
        "2976",
        "2978",
        "298",
        "2980",
        "29822",
        "2983",
        "2985",
        "2988",
        "2989",
        "2990",
        "2994",
        "2995",
        "2997",
        "30",
        "3000",
        "300179",
        "3002",
        "300298",
        "3003",
        "300305",
        "300373",
        "300385",
        "3004",
        "300493",
        "300536",
        "300570",
        "300573",
        "3006",
        "300605",
        "300751",
        "3008",
        "3010",
        "3011",
        "3015",
        "3016",
        "3019",
        "302",
        "3023",
        "3027",
        "3032",
        "3033",
        "3034",
        "3035",
        "3038",
        "30391",
        "3041",
        "3042",
        "3044",
        "3047",
        "3051",
        "3052",
        "3055",
        "3057",
        "306",
        "3063",
        "306498",
        "306511",
        "306542",
        "306550",
        "306617",
        "306669",
        "306674",
        "306682",
        "306686",
        "306692",
        "306731",
        "306734",
        "306741",
        "3068",
        "307",
        "3071",
        "3074",
        "3077",
        "3078",
        "3079",
        "308",
        "3080",
        "3082",
        "3085",
        "308552",
        "309031",
        "309108",
        "3092",
        "309246",
        "30925",
        "309256",
        "309263",
        "309271",
        "309282",
        "309288",
        "3093",
        "3095",
        "3097",
        "3098",
        "309854",
        "3099",
        "31",
        "3101",
        "3103",
        "3104",
        "3107",
        "3109",
        "3111",
        "31112",
        "31142",
        "3115",
        "31150",
        "312",
        "31202",
        "31204",
        "31205",
        "3121",
        "3124",
        "3129",
        "313",
        "3130",
        "3132",
        "3134",
        "3135",
        "3137",
        "313772",
        "313781",
        "3138",
        "313855",
        "313892",
        "313906",
        "313947",
        "314",
        "314034",
        "3143",
        "314389",
        "3144",
        "314404",
        "314473",
        "314478",
        "3145",
        "314575",
        "314585",
        "314588",
        "314603",
        "314621",
        "314632",
        "314647",
        "314652",
        "314655",
        "314679",
        "314769",
        "314795",
        "314802",
        "314811",
        "314911",
        "314918",
        "314978",
        "315",
        "3151",
        "3152",
        "3156",
        "3157",
        "316",
        "3162",
        "3163",
        "3164",
        "3165",
        "3166",
        "3168",
        "3169",
        "317",
        "31709",
        "3173",
        "3175",
        "3176",
        "3177",
        "318",
        "3180",
        "3181",
        "31824",
        "31825",
        "31826",
        "3186",
        "3188",
        "3189",
        "3191",
        "319171",
        "319182",
        "319195",
        "319199",
        "319213",
        "319218",
        "319251",
        "3193",
        "3194",
        "319487",
        "319514",
        "319552",
        "3196",
        "319600",
        "319671",
        "319675",
        "3197",
        "3198",
        "3199",
        "32",
        "320",
        "3201",
        "3202",
        "3203",
        "320355",
        "320360",
        "320365",
        "320370",
        "320375",
        "320380",
        "320385",
        "320391",
        "320396",
        "3204",
        "320401",
        "320406",
        "320411",
        "3205",
        "3206",
        "3207",
        "3208",
        "321",
        "3210",
        "3214",
        "3216",
        "3217",
        "3218",
        "3219",
        "322",
        "3220",
        "3222",
        "3224",
        "3225",
        "3226",
        "3230",
        "3232",
        "3233",
        "3235",
        "3236",
        "3237",
        "3238",
        "3239",
        "324",
        "3240",
        "3241",
        "3242",
        "324262",
        "324290",
        "3243",
        "324313",
        "324410",
        "324416",
        "324422",
        "324442",
        "324540",
        "324575",
        "324581",
        "324588",
        "3246",
        "324604",
        "324625",
        "324636",
        "324703",
        "324708",
        "324713",
        "324723",
        "324737",
        "3248",
        "324964",
        "325",
        "3250",
        "325124",
        "3253",
        "325345",
        "3255",
        "3258",
        "326",
        "3260",
        "3261",
        "3265",
        "3266",
        "3267",
        "3268",
        "3269",
        "327",
        "3270",
        "328",
        "3283",
        "3286",
        "3287",
        "329",
        "329178",
        "329224",
        "329228",
        "329249",
        "329252",
        "329284",
        "329308",
        "329314",
        "329329",
        "329336",
        "3294",
        "329466",
        "329475",
        "329478",
        "32960",
        "3299",
        "329918",
        "329967",
        "329971",
        "33",
        "330",
        "330001",
        "33001",
        "330015",
        "330021",
        "330050",
        "330054",
        "330064",
        "3301",
        "3303",
        "3304",
        "3305",
        "3306",
        "33069",
        "3307",
        "3309",
        "331",
        "3310",
        "33110",
        "33111",
        "3312",
        "331206",
        "331235",
        "3314",
        "3316",
        "3318",
        "3319",
        "3320",
        "33208",
        "3322",
        "33226",
        "3325",
        "3327",
        "33276",
        "3329",
        "333",
        "33314",
        "3332",
        "33355",
        "33364",
        "3337",
        "3339",
        "33402",
        "33408",
        "3342",
        "3344",
        "33445",
        "3346",
        "3347",
        "33475",
        "3348",
        "335",
        "3350",
        "3352",
        "3353",
        "33574",
        "33577",
        "3361",
        "3366",
        "3369",
        "337",
        "3374",
        "3375",
        "3376",
        "3377",
        "3378",
        "3379",
        "3380",
        "3384",
        "3385",
        "3386",
        "3389",
        "3392",
        "340",
        "3400",
        "3404",
        "3405",
        "3406",
        "3408",
        "3409",
        "3411",
        "3412",
        "3416",
        "3417",
        "342",
        "34217",
        "3424",
        "3426",
        "3429",
        "343",
        "3433",
        "3434",
        "3437",
        "3440",
        "3447",
        "3448",
        "3449",
        "345",
        "3451",
        "34515",
        "34516",
        "3452",
        "34527",
        "3453",
        "3454",
        "3455",
        "3456",
        "34587",
        "3459",
        "346",
        "3463",
        "3464",
        "3465",
        "3467",
        "3469",
        "347",
        "3471",
        "3472",
        "3473",
        "3474",
        "348",
        "349",
        "35",
        "35069",
        "35078",
        "35093",
        "35098",
        "35099",
        "351",
        "35107",
        "35122",
        "35125",
        "35173",
        "352",
        "352403",
        "352447",
        "352470",
        "352479",
        "352490",
        "352530",
        "352540",
        "352577",
        "352582",
        "352596",
        "352641",
        "352649",
        "352665",
        "352675",
        "352682",
        "352723",
        "352731",
        "353",
        "353253",
        "353277",
        "353281",
        "353284",
        "353298",
        "353327",
        "354",
        "355",
        "356",
        "35612",
        "35664",
        "35687",
        "35689",
        "356961",
        "356996",
        "357001",
        "35701",
        "357043",
        "357058",
        "35706",
        "357074",
        "35710",
        "357154",
        "357175",
        "357225",
        "35737",
        "358",
        "35858",
        "35878",
        "35909",
        "36",
        "360",
        "361",
        "36234",
        "36237",
        "36238",
        "36258",
        "363400",
        "363417",
        "363429",
        "363432",
        "363444",
        "363454",
        "363523",
        "363528",
        "363549",
        "363558",
        "363611",
        "363618",
        "363623",
        "363654",
        "363659",
        "36367",
        "363686",
        "363700",
        "363705",
        "363710",
        "363741",
        "36382",
        "36386",
        "36387",
        "363958",
        "363965",
        "36397",
        "364",
        "364028",
        "364055",
        "36412",
        "36426",
        "364577",
        "365",
        "366",
        "367",
        "368",
        "36899",
        "369",
        "36913",
        "369837",
        "369840",
        "369847",
        "369873",
        "369891",
        "369929",
        "369939",
        "369950",
        "37",
        "370",
        "370010",
        "370022",
        "370079",
        "370091",
        "370097",
        "370103",
        "370348",
        "37042",
        "370921",
        "370924",
        "370927",
        "370930",
        "370943",
        "370959",
        "370968",
        "370980",
        "370997",
        "371",
        "371364",
        "371428",
        "37202",
        "373",
        "375",
        "37553",
        "376",
        "37612",
        "377",
        "37748",
        "379",
        "38",
        "380",
        "381",
        "382",
        "384",
        "385",
        "388",
        "39041",
        "39044",
        "391",
        "391307",
        "391372",
        "391408",
        "391411",
        "391417",
        "391428",
        "391457",
        "391474",
        "391487",
        "391641",
        "391646",
        "391665",
        "391673",
        "392",
        "393",
        "394",
        "395",
        "396",
        "397",
        "397590",
        "397612",
        "397685",
        "397695",
        "397709",
        "397715",
        "397725",
        "397744",
        "397933",
        "397941",
        "397946",
        "397951",
        "397973",
        "398063",
        "398069",
        "398073",
        "398079",
        "39812",
        "398124",
        "398147",
        "398156",
        "398173",
        "398189",
        "399",
        "399058",
        "399081",
        "399086",
        "399096",
        "399103",
        "399180",
        "399805",
        "399808",
        "40",
        "400",
        "401768",
        "401777",
        "401780",
        "401785",
        "401795",
        "401800",
        "401805",
        "401810",
        "401815",
        "401820",
        "401830",
        "401835",
        "401840",
        "401849",
        "401866",
        "401901",
        "401911",
        "401923",
        "401935",
        "401942",
        "401945",
        "401953",
        "401973",
        "402075",
        "403",
        "40366",
        "404",
        "404440",
        "404443",
        "404448",
        "404451",
        "404454",
        "404473",
        "404493",
        "404499",
        "405",
        "407",
        "408",
        "409",
        "40923",
        "41",
        "411493",
        "411511",
        "411515",
        "411527",
        "411536",
        "411543",
        "411590",
        "411593",
        "411602",
        "411629",
        "411634",
        "411641",
        "411696",
        "411703",
        "411709",
        "411777",
        "411986",
        "412",
        "412035",
        "412057",
        "412066",
        "412069",
        "412217",
        "414",
        "415",
        "416",
        "417",
        "41751",
        "419",
        "42",
        "420179",
        "420485",
        "420492",
        "420561",
        "42062",
        "420741",
        "420794",
        "422",
        "423",
        "423275",
        "423296",
        "423479",
        "424",
        "424016",
        "424019",
        "424107",
        "425",
        "42642",
        "42665",
        "427",
        "42775",
        "428",
        "429",
        "43",
        "43116",
        "431329",
        "431361",
        "432",
        "43393",
        "434179",
        "435387",
        "435628",
        "435638",
        "435651",
        "435660",
        "435804",
        "435934",
        "435938",
        "436",
        "436003",
        "436141",
        "436144",
        "436151",
        "436174",
        "436182",
        "436245",
        "436252",
        "436271",
        "436274",
        "437",
        "437572",
        "438114",
        "438134",
        "438178",
        "438213",
        "438216",
        "438274",
        "439",
        "439167",
        "439218",
        "439232",
        "439822",
        "44",
        "440354",
        "440437",
        "440713",
        "440727",
        "441",
        "442",
        "442835",
        "443167",
        "443811",
        "444",
        "444002",
        "444013",
        "444051",
        "444072",
        "444077",
        "444099",
        "444463",
        "444490",
        "445038",
        "445062",
        "446",
        "447",
        "447753",
        "447757",
        "447760",
        "447788",
        "447877",
        "447896",
        "447980",
        "447997",
        "448237",
        "44890",
        "449280",
        "449285",
        "449291",
        "449395",
        "449400",
        "449427",
        "449432",
        "449563",
        "45",
        "452",
        "453499",
        "453504",
        "453510",
        "453521",
        "453533",
        "454",
        "45448",
        "45452",
        "45453",
        "454836",
        "454840",
        "454887",
        "455",
        "456312",
        "456328",
        "457",
        "457050",
        "457059",
        "457083",
        "457193",
        "457205",
        "457212",
        "457240",
        "457260",
        "457279",
        "457284",
        "457351",
        "457359",
        "457365",
        "457395",
        "457485",
        "458798",
        "458803",
        "459033",
        "459056",
        "459061",
        "459070",
        "459074",
        "46",
        "46059",
        "461",
        "46348",
        "464",
        "464282",
        "464288",
        "464306",
        "464311",
        "464318",
        "464321",
        "464329",
        "464343",
        "464370",
        "464440",
        "464453",
        "464738",
        "46486",
        "46487",
        "46488",
        "465",
        "46532",
        "465508",
        "46627",
        "466650",
        "466677",
        "466688",
        "466722",
        "466768",
        "466791",
        "466794",
        "466926",
        "466934",
        "466943",
        "466950",
        "46724",
        "468620",
        "468631",
        "468661",
        "468678",
        "468699",
        "468726",
        "469",
        "47",
        "470",
        "47045",
        "47159",
        "474",
        "475",
        "47612",
        "476126",
        "477",
        "477673",
        "477774",
        "477781",
        "477817",
        "477993",
        "478",
        "478029",
        "48",
        "480",
        "480520",
        "480536",
        "480864",
        "480880",
        "480898",
        "480907",
        "481",
        "48104",
        "481152",
        "482",
        "482601",
        "48372",
        "48377",
        "48431",
        "48435",
        "485",
        "485350",
        "485405",
        "485421",
        "486",
        "48652",
        "486815",
        "48686",
        "487796",
        "487825",
        "488",
        "48818",
        "488191",
        "488333",
        "488434",
        "488437",
        "488594",
        "488613",
        "488618",
        "488627",
        "488632",
        "488635",
        "488642",
        "488650",
        "48918",
        "49",
        "49041",
        "49042",
        "492",
        "493",
        "49382",
        "494",
        "494344",
        "494424",
        "494526",
        "494541",
        "495",
        "49566",
        "495818",
        "495875",
        "496641",
        "496689",
        "496756",
        "496790",
        "497764",
        "49804",
        "49827",
        "498359",
        "499",
        "5",
        "50",
        "500",
        "500055",
        "500095",
        "500144",
        "500150",
        "500159",
        "500166",
        "500180",
        "500533",
        "500545",
        "501",
        "502",
        "502423",
        "502434",
        "50251",
        "503",
        "504476",
        "505",
        "505216",
        "505237",
        "505248",
        "505395",
        "505652",
        "506",
        "506353",
        "506358",
        "507",
        "508",
        "50809",
        "50810",
        "50811",
        "50812",
        "50814",
        "50815",
        "50817",
        "508410",
        "508488",
        "508498",
        "508533",
        "508542",
        "509",
        "50918",
        "50942",
        "50943",
        "50944",
        "50945",
        "51",
        "510",
        "51083",
        "511",
        "51188",
        "512",
        "51208",
        "512260",
        "513436",
        "513456",
        "514",
        "51608",
        "51636",
        "517",
        "51890",
        "52",
        "520",
        "52022",
        "52047",
        "52055",
        "52056",
        "521",
        "521219",
        "521258",
        "521308",
        "521390",
        "521406",
        "521411",
        "521426",
        "521445",
        "522077",
        "523",
        "52368",
        "524",
        "52416",
        "52417",
        "52427",
        "52429",
        "52430",
        "525",
        "52503",
        "525731",
        "526",
        "527497",
        "528",
        "528084",
        "529",
        "52901",
        "529665",
        "529799",
        "529808",
        "529962",
        "529965",
        "529970",
        "53",
        "530",
        "53035",
        "530838",
        "530983",
        "531",
        "531151",
        "53271",
        "53296",
        "533",
        "53351",
        "53372",
        "534",
        "535",
        "53583",
        "536467",
        "536471",
        "536516",
        "536532",
        "536545",
        "53693",
        "53697",
        "537",
        "53715",
        "53719",
        "53721",
        "538",
        "54",
        "540",
        "54028",
        "54057",
        "541423",
        "542306",
        "542323",
        "54247",
        "54251",
        "542592",
        "542643",
        "543",
        "543470",
        "54370",
        "544254",
        "544482",
        "544488",
        "544503",
        "545",
        "54595",
        "548",
        "549",
        "55",
        "550",
        "551",
        "552",
        "555874",
        "555905",
        "556",
        "556030",
        "556037",
        "55654",
        "556955",
        "557",
        "557003",
        "558",
        "55881",
        "559",
        "56",
        "560",
        "561",
        "561854",
        "562",
        "562639",
        "563",
        "56304",
        "56305",
        "563609",
        "563612",
        "563991",
        "564",
        "564003",
        "564178",
        "56425",
        "565",
        "565612",
        "565624",
        "565899",
        "566",
        "566943",
        "567",
        "567544",
        "567546",
        "567548",
        "567983",
        "568",
        "568051",
        "569",
        "57",
        "570",
        "570422",
        "57145",
        "57196",
        "572",
        "572333",
        "572798",
        "573",
        "573278",
        "575",
        "576",
        "576283",
        "577",
        "57777",
        "57782",
        "578",
        "579",
        "58",
        "580",
        "581",
        "582",
        "583",
        "584",
        "585",
        "586",
        "587",
        "588",
        "589",
        "59",
        "590",
        "59135",
        "59181",
        "592",
        "59298",
        "59303",
        "59315",
        "596",
        "597",
        "598",
        "6",
        "60",
        "600",
        "60015",
        "60025",
        "60026",
        "60030",
        "60032",
        "60033",
        "60039",
        "60040",
        "602",
        "603",
        "606",
        "609",
        "61",
        "610",
        "611",
        "614",
        "615",
        "616",
        "617",
        "618",
        "62",
        "621",
        "622",
        "624",
        "626",
        "627",
        "628",
        "63",
        "631",
        "63259",
        "63260",
        "63273",
        "63275",
        "633",
        "634",
        "63440",
        "63442",
        "63446",
        "63455",
        "635",
        "636",
        "637",
        "638",
        "63862",
        "639",
        "64",
        "640",
        "641",
        "642",
        "64280",
        "643",
        "644",
        "646",
        "647",
        "64734",
        "64739",
        "64741",
        "64743",
        "64744",
        "64745",
        "64752",
        "64753",
        "64754",
        "64755",
        "648",
        "649",
        "65",
        "650",
        "652",
        "65250",
        "65282",
        "65285",
        "65286",
        "65288",
        "653",
        "654",
        "655",
        "656",
        "65681",
        "65682",
        "65683",
        "65684",
        "65759",
        "659",
        "660",
        "661",
        "662",
        "663",
        "664",
        "66518",
        "66529",
        "666",
        "66624",
        "66625",
        "66627",
        "66628",
        "66629",
        "66630",
        "66631",
        "66633",
        "66634",
        "66637",
        "66661",
        "667",
        "668",
        "67",
        "67036",
        "67041",
        "67042",
        "67043",
        "67044",
        "67045",
        "67046",
        "67047",
        "67048",
        "672",
        "673",
        "675",
        "676",
        "677",
        "678",
        "679",
        "68",
        "681",
        "682",
        "683",
        "684",
        "69061",
        "69063",
        "69076",
        "69077",
        "69078",
        "69085",
        "69087",
        "69125",
        "69126",
        "69663",
        "69665",
        "69735",
        "69736",
        "69744",
        "69745",
        "699",
        "7",
        "70",
        "700",
        "701",
        "702",
        "703",
        "704",
        "70472",
        "70474",
        "70475",
        "70476",
        "70482",
        "705",
        "70567",
        "70578",
        "70587",
        "70588",
        "70589",
        "70591",
        "70592",
        "70593",
        "70594",
        "70595",
        "707",
        "708",
        "709",
        "71",
        "710",
        "71211",
        "71212",
        "71213",
        "71267",
        "71272",
        "71273",
        "71275",
        "71276",
        "71277",
        "71289",
        "713",
        "71493",
        "71505",
        "71517",
        "71518",
        "71519",
        "71526",
        "71528",
        "71529",
        "716",
        "718",
        "72",
        "720",
        "721",
        "722",
        "723",
        "724",
        "725",
        "726",
        "727",
        "728",
        "729",
        "73",
        "730",
        "731",
        "732",
        "73223",
        "73224",
        "73229",
        "73230",
        "73245",
        "73246",
        "73247",
        "73256",
        "73263",
        "73267",
        "73272",
        "73273",
        "733",
        "735",
        "737",
        "738",
        "739",
        "74",
        "740",
        "742",
        "743",
        "744",
        "745",
        "746",
        "747",
        "750",
        "752",
        "75233",
        "75234",
        "75249",
        "753",
        "75325",
        "75373",
        "75374",
        "75376",
        "75377",
        "75378",
        "75382",
        "75389",
        "75392",
        "754",
        "75496",
        "75497",
        "755",
        "75508",
        "75563",
        "75564",
        "75565",
        "75566",
        "75567",
        "757",
        "758",
        "75840",
        "75857",
        "75858",
        "759",
        "760",
        "761",
        "763",
        "764",
        "765",
        "766",
        "767",
        "769",
        "770",
        "772",
        "77258",
        "77259",
        "77260",
        "77261",
        "77293",
        "77296",
        "77297",
        "77298",
        "77299",
        "773",
        "77300",
        "77301",
        "774",
        "776",
        "777",
        "778",
        "779",
        "781",
        "782",
        "783",
        "785",
        "786",
        "79",
        "790",
        "79076",
        "79078",
        "79083",
        "79084",
        "79085",
        "79086",
        "79087",
        "79093",
        "79094",
        "79095",
        "79096",
        "79097",
        "79099",
        "791",
        "79100",
        "79101",
        "79102",
        "79106",
        "79107",
        "79113",
        "79124",
        "79126",
        "79127",
        "79128",
        "79129",
        "79133",
        "79134",
        "79135",
        "79136",
        "79137",
        "79138",
        "79139",
        "79140",
        "79141",
        "79144",
        "79145",
        "79147",
        "79148",
        "79149",
        "79151",
        "79152",
        "79153",
        "79155",
        "79156",
        "79159",
        "79168",
        "792",
        "79230",
        "79233",
        "79234",
        "79235",
        "79237",
        "79238",
        "79239",
        "79241",
        "79242",
        "79243",
        "79244",
        "79246",
        "79254",
        "79255",
        "79259",
        "79262",
        "79263",
        "79264",
        "79273",
        "79276",
        "79277",
        "79278",
        "79279",
        "79280",
        "79281",
        "79282",
        "79283",
        "79284",
        "79292",
        "79299",
        "793",
        "79301",
        "79302",
        "79303",
        "79312",
        "79314",
        "79318",
        "79319",
        "79320",
        "79321",
        "79322",
        "79323",
        "79324",
        "79325",
        "79326",
        "79327",
        "79328",
        "79329",
        "79330",
        "79332",
        "79333",
        "79345",
        "79350",
        "79351",
        "79357",
        "79358",
        "79394",
        "79395",
        "79396",
        "79397",
        "79399",
        "794",
        "79400",
        "79401",
        "79402",
        "79403",
        "79404",
        "79405",
        "79406",
        "79408",
        "79409",
        "79410",
        "79411",
        "79430",
        "79431",
        "79432",
        "79433",
        "79434",
        "79435",
        "79443",
        "79444",
        "79445",
        "79452",
        "79455",
        "79456",
        "79457",
        "79473",
        "79474",
        "79476",
        "79477",
        "79478",
        "79480",
        "79481",
        "79492",
        "79493",
        "79499",
        "79500",
        "79501",
        "79503",
        "79506",
        "796",
        "79665",
        "797",
        "798",
        "799",
        "8",
        "800",
        "801",
        "803",
        "805",
        "808",
        "809",
        "81",
        "810",
        "811",
        "812",
        "813",
        "816",
        "818",
        "819",
        "82",
        "820",
        "821",
        "822",
        "824",
        "827",
        "828",
        "829",
        "83",
        "833",
        "83313",
        "83317",
        "834",
        "83450",
        "83452",
        "83453",
        "83454",
        "83461",
        "83463",
        "83465",
        "83468",
        "83469",
        "83472",
        "83473",
        "83597",
        "83600",
        "83601",
        "83617",
        "83619",
        "83620",
        "83628",
        "83629",
        "838",
        "839",
        "84",
        "840",
        "84064",
        "84085",
        "84090",
        "841",
        "84142",
        "845",
        "846",
        "847",
        "848",
        "849",
        "851",
        "85112",
        "85128",
        "85138",
        "85162",
        "85163",
        "85164",
        "85165",
        "85166",
        "85167",
        "85168",
        "85169",
        "85170",
        "85172",
        "85173",
        "85174",
        "85175",
        "85179",
        "85184",
        "85193",
        "85194",
        "85197",
        "85198",
        "85199",
        "85201",
        "85202",
        "85203",
        "85212",
        "85273",
        "85274",
        "85275",
        "85276",
        "85277",
        "85278",
        "85279",
        "85280",
        "85282",
        "85283",
        "85284",
        "85285",
        "85286",
        "85287",
        "85288",
        "85290",
        "85292",
        "85293",
        "85294",
        "85295",
        "85297",
        "853",
        "85317",
        "85319",
        "85320",
        "85321",
        "85322",
        "85323",
        "85324",
        "85325",
        "85326",
        "85327",
        "85329",
        "85332",
        "85334",
        "85335",
        "85336",
        "85338",
        "85408",
        "85410",
        "85414",
        "85435",
        "85436",
        "85438",
        "85443",
        "85445",
        "85446",
        "85447",
        "85448",
        "857",
        "858",
        "859",
        "860",
        "861",
        "863",
        "86309",
        "867",
        "86788",
        "868",
        "86812",
        "86814",
        "86816",
        "86818",
        "86820",
        "86822",
        "86839",
        "86841",
        "86843",
        "86884",
        "86893",
        "869",
        "86909",
        "86914",
        "86918",
        "86919",
        "86923",
        "87",
        "870",
        "871",
        "873",
        "87503",
        "87876",
        "87884",
        "88",
        "881",
        "882",
        "884",
        "886",
        "88616",
        "88618",
        "88619",
        "88621",
        "88628",
        "88629",
        "88635",
        "88637",
        "88639",
        "88643",
        "88644",
        "88661",
        "88673",
        "887",
        "888",
        "889",
        "890",
        "891",
        "892",
        "893",
        "894",
        "895",
        "896",
        "897",
        "89838",
        "89842",
        "89843",
        "89844",
        "899",
        "89936",
        "89937",
        "89938",
        "9",
        "90",
        "900",
        "90000",
        "90003",
        "90023",
        "90024",
        "90026",
        "90033",
        "90035",
        "90036",
        "90037",
        "90038",
        "90042",
        "90044",
        "90045",
        "90050",
        "90051",
        "90060",
        "90062",
        "90064",
        "90065",
        "90068",
        "901",
        "90103",
        "90117",
        "90153",
        "90154",
        "90156",
        "90157",
        "90158",
        "90159",
        "90160",
        "90186",
        "902",
        "90280",
        "90283",
        "90289",
        "90291",
        "903",
        "90301",
        "90307",
        "90308",
        "90321",
        "90322",
        "90324",
        "90340",
        "90342",
        "90348",
        "90349",
        "90354",
        "90362",
        "90363",
        "904",
        "905",
        "906",
        "90646",
        "90647",
        "90650",
        "90652",
        "90653",
        "90654",
        "90658",
        "90673",
        "90674",
        "90695",
        "90790",
        "90791",
        "90793",
        "90794",
        "90795",
        "90796",
        "90797",
        "908",
        "909",
        "90970",
        "91",
        "910",
        "911",
        "91130",
        "91131",
        "91132",
        "91133",
        "91135",
        "91138",
        "912",
        "913",
        "91347",
        "91348",
        "91349",
        "91350",
        "91351",
        "91354",
        "91355",
        "91387",
        "91416",
        "915",
        "91500",
        "91546",
        "91547",
        "916",
        "92",
        "920",
        "92050",
        "921",
        "922",
        "926",
        "927",
        "929",
        "93",
        "930",
        "931",
        "93101",
        "93109",
        "93110",
        "93111",
        "93126",
        "93160",
        "932",
        "93256",
        "93258",
        "93259",
        "93260",
        "93262",
        "93267",
        "93271",
        "93274",
        "93283",
        "93284",
        "93296",
        "93298",
        "93299",
        "93302",
        "93304",
        "93307",
        "93308",
        "93311",
        "93314",
        "93315",
        "93316",
        "93317",
        "93320",
        "93321",
        "93322",
        "93323",
        "93324",
        "93325",
        "93328",
        "93329",
        "93333",
        "93346",
        "93351",
        "93352",
        "93356",
        "93357",
        "93359",
        "93360",
        "93383",
        "93384",
        "93387",
        "93388",
        "93394",
        "93396",
        "93397",
        "93399",
        "93400",
        "93402",
        "93403",
        "93404",
        "93405",
        "93406",
        "93409",
        "93430",
        "93473",
        "93474",
        "93476",
        "935",
        "93552",
        "93598",
        "93599",
        "93600",
        "93672",
        "939",
        "93924",
        "93925",
        "93926",
        "93928",
        "93929",
        "93930",
        "93932",
        "93941",
        "93945",
        "93946",
        "93947",
        "93950",
        "93952",
        "93958",
        "94058",
        "94059",
        "94063",
        "94064",
        "94065",
        "94066",
        "94068",
        "94080",
        "94083",
        "94088",
        "94089",
        "94090",
        "94093",
        "94095",
        "941",
        "94122",
        "94124",
        "94125",
        "94147",
        "945",
        "949",
        "95",
        "950",
        "95159",
        "952",
        "95232",
        "95409",
        "95427",
        "95428",
        "95429",
        "95433",
        "95434",
        "95455",
        "95459",
        "95494",
        "95496",
        "955",
        "95512",
        "95513",
        "95613",
        "95619",
        "95626",
        "95699",
        "957",
        "95706",
        "95707",
        "95712",
        "95713",
        "95715",
        "95716",
        "95717",
        "95719",
        "95720",
        "958",
        "959",
        "96",
        "96061",
        "96092",
        "96097",
        "96121",
        "96123",
        "96125",
        "96129",
        "96147",
        "96148",
        "96149",
        "96167",
        "96168",
        "96169",
        "96170",
        "96176",
        "96179",
        "96180",
        "96181",
        "96182",
        "96183",
        "96184",
        "96190",
        "96191",
        "96201",
        "96253",
        "96263",
        "96264",
        "963",
        "96334",
        "96369",
        "965",
        "966",
        "968",
        "969",
        "97",
        "970",
        "971",
        "972",
        "97214",
        "97229",
        "97230",
        "97240",
        "97244",
        "97261",
        "97278",
        "97279",
        "97280",
        "97282",
        "97283",
        "97285",
        "97286",
        "97287",
        "97289",
        "97290",
        "97292",
        "97297",
        "973",
        "97330",
        "97332",
        "97335",
        "97336",
        "97337",
        "97341",
        "97349",
        "97355",
        "97360",
        "974",
        "976",
        "97685",
        "977",
        "978",
        "98",
        "980",
        "98028",
        "981",
        "98292",
        "98293",
        "983",
        "98375",
        "98673",
        "98754",
        "98755",
        "98756",
        "98757",
        "98758",
        "98759",
        "98760",
        "98761",
        "98762",
        "98763",
        "98764",
        "98765",
        "98766",
        "98767",
        "98768",
        "98769",
        "98771",
        "98772",
        "98773",
        "98784",
        "98791",
        "98793",
        "98794",
        "98795",
        "98797",
        "98798",
        "988",
        "98805",
        "98806",
        "98807",
        "98808",
        "98809",
        "98810",
        "98811",
        "98818",
        "98820",
        "98826",
        "98827",
        "98848",
        "98849",
        "98850",
        "98853",
        "98855",
        "98863",
        "98870",
        "98878",
        "98879",
        "98880",
        "98881",
        "98889",
        "98890",
        "98892",
        "98895",
        "98896",
        "98897",
        "989",
        "98902",
        "98905",
        "98907",
        "98908",
        "98909",
        "98911",
        "98912",
        "98913",
        "98914",
        "98915",
        "98916",
        "98933",
        "98934",
        "98960",
        "98964",
        "98969",
        "98973",
        "98976",
        "98977",
        "99",
        "990",
        "99000",
        "99013",
        "99014",
        "99015",
        "99027",
        "99050",
        "991",
        "99103",
        "99104",
        "99105",
        "99106",
        "99125",
        "99147",
        "99226",
        "99228",
        "99329",
        "99330",
        "994",
        "99413",
        "99429",
        "99642",
        "99657",
        "99688",
        "99725",
        "99734",
        "99735",
        "99736",
        "99742",
        "99745",
        "99748",
        "99750",
        "99771",
        "99772",
        "99776",
        "99798",
        "998",
        "99802",
        "99803",
        "99811",
        "99812",
        "99818",
        "99819",
        "99824",
        "99825",
        "99826",
        "99827",
        "99828",
        "99829",
        "99832",
        "99843",
        "99852",
        "99857",
        "99867",
        "99868",
        "99877",
        "99878",
        "99879",
        "99880",
        "99885",
        "99886",
        "99889",
        "999",
        "99901",
        "99921",
        "99925",
        "99926",
        "99927",
        "99928",
        "99939",
        "99940",
        "99944",
        "99947",
        "99949",
        "99950",
        "99953",
        "99965",
        "99966",
        "99967",
        "99969",
        "99971",
        "99976",
        "99977",
        "99978"
      ]
    }
  }
}
